camonline/__init__.py
camonline/camera.py
camonline/cli.py
camonline/config.py
camonline/exceptions.py
camonline/log.py
camonline/monitor.py
camonline/server.py
camonline/static/config.toml
camonline-0.1.5.dist-info/METADATA
camonline-0.1.5.dist-info/WHEEL
camonline-0.1.5.dist-info/entry_points.txt
camonline-0.1.5.dist-info/licenses/LICENSE
camonline-0.1.5.dist-info/RECORD
