Metadata-Version: 2.1
Name: camonline
Version: 0.1.5
Summary: camonline
Project-URL: Source, https://github.com/wh1isper/camonline
Author-email: wh1isper <9573586@qq.com>
License: BSD 3-Clause License
License-File: LICENSE
Keywords: camonline
Classifier: Programming Language :: Python :: 3.8
Classifier: Programming Language :: Python :: 3.9
Classifier: Programming Language :: Python :: 3.10
Classifier: Programming Language :: Python :: 3.11
Requires-Python: >=3.8
Requires-Dist: click
Requires-Dist: loguru
Requires-Dist: opencv-python-headless
Requires-Dist: tomli
Requires-Dist: tomli-w
Provides-Extra: test
Requires-Dist: pytest; extra == 'test'
Requires-Dist: pytest-cov; extra == 'test'
